README.md
setup.cfg
setup.py
cryptocomp.egg-info/PKG-INFO
cryptocomp.egg-info/SOURCES.txt
cryptocomp.egg-info/dependency_links.txt
cryptocomp.egg-info/requires.txt
cryptocomp.egg-info/top_level.txt
cryptocompy/__init__.py
cryptocompy/coin.py
cryptocompy/helper_functions.py
cryptocompy/mining.py
cryptocompy/price.py
cryptocompy/rest.py
cryptocompy/top.py