Metadata-Version: 1.2
Name: cryptocomp
Version: 0.1
Summary: Simple wrapper for the public Cryptocompare API.
Home-page: https://github.com/wildsmileofbutterfly/cryptocompy
Author: Margarita Rudenskaya
Author-email: margo.rudenskaya@gmail.com
License: MIT
Download-URL: https://github.com/wildsmileofbutterfly/cryptocompy/archive/0.1.1.dev2.tar.gz
Platform: UNKNOWN
Requires-Python: >=3
